<?xml version="1.0" ?>

<container xmlns="http://symfony.com/schema/dic/services"
    xmlns:xsi="http://www.w3.org/2001/XMLSchema-instance"
    xsi:schemaLocation="http://symfony.com/schema/dic/services http://symfony.com/schema/dic/services/services-1.0.xsd">
    <services>
        <service id="pumukit_live.live" class="Pumukit\LiveBundle\Services\LiveService">
        </service>
        <service id="pumukit_live.twig_extension" class="Pumukit\LiveBundle\Twig\LiveTwigExtension">
            <argument type="service" id="doctrine_mongodb.odm.document_manager" />
            <argument type="service" id="pumukit_live.live" />
            <tag name="twig.extension"/>
        </service>
        <service id="pumukitlive.legacyeventpic" class="Pumukit\LiveBundle\Services\LegacyEventPicService">
            <argument type="service" id="doctrine_mongodb.odm.document_manager"/>
            <argument>%pumukit2.uploads_dir%/pic</argument>
            <argument>%pumukit2.uploads_url%/pic</argument>
            <argument>%pumukit2.delete_on_disk%</argument>
        </service>
    </services>
</container>
